base/__init__.py
base/type_input.py
py_helpers/__init__.py
py_helpers/base/__init__.py
py_helpers/base/type_input.py
python_helpers/__init__.py
python_helpers/base/__init__.py
python_helpers/base/type_input.py
py_helpers_icyi2i-0.0.1.dist-info/LICENSE
py_helpers_icyi2i-0.0.1.dist-info/METADATA
py_helpers_icyi2i-0.0.1.dist-info/WHEEL
py_helpers_icyi2i-0.0.1.dist-info/top_level.txt
py_helpers_icyi2i-0.0.1.dist-info/RECORD
