Metadata-Version: 2.1
Name: py-helpers-icyi2i
Version: 0.0.1
Summary: A collection of helper functions for rapid development!
Home-page: https://github.com/icyi2i/python-helpers
Author: Sarthak Gambhir
Author-email: sarthak3gambhir@gmail.com
License: UNKNOWN
Project-URL: Bug Tracker, https://github.com/icyi2i/python-helpers/issues
Platform: UNKNOWN
Classifier: Programming Language :: Python :: 3
Classifier: License :: OSI Approved :: GNU General Public License v3 or later (GPLv3+)
Classifier: Operating System :: OS Independent
Requires-Python: >=3.6
License-File: LICENSE
